{
  "type": "FeatureCollection",
  "features": [
    {
      "type": "Feature",
      "geometry": {
        "type": "Point",
        "coordinates": [
          129.7153628,
          33.1746963
        ]
      },
      "properties": {
        "marker-symbol": "doctor-15",
        "marker-color": "#000000",
        "name": "Ikeda Vet Clinic",
        "address": "1002-37 Hinochō, Sasebo-shi, Nagasaki-ken 858-0923",
        "telephone": "0956-28-4045",
        "website": "",
        "english": "Yes",
        "note": "Closed Thursdays and national holidays."
      }
    },
    {
      "type": "Feature",
      "geometry": {
        "type": "Point",
        "coordinates": [
          129.7047802,
          33.1666297
        ]
      },
      "properties": {
        "marker-symbol": "doctor-15",
        "marker-color": "#000000",
        "name": "Hamaguchi Vet Clinic",
        "address": "10-8 Kamishimacho, Sasebo, Nagasaki Prefecture 857-0067",
        "telephone": "0956-25-9914",
        "website": "http://www.hamaguchi-vet.jp",
        "english": "Some",
        "note": "Closed Sunday and national holidays."
      }
    },
    {
      "type": "Feature",
      "geometry": {
        "type": "Point",
        "coordinates": [
          129.8035747,
          33.1360707
        ]
      },
      "properties": {
        "marker-symbol": "doctor-15",
        "marker-color": "#000000",
        "name": "Mine Pet Clinic",
        "address": "1101-22 Gonjōjichō, Sasebo-shi, Nagasaki-ken 859-3213",
        "telephone": "0956-38-9555",
        "website": "",
        "english": "Some",
        "note": "Closed Sunday and national holidays."
      }
    },
    {
      "type": "Feature",
      "geometry": {
        "type": "Point",
        "coordinates": [
          129.772914,
          33.1681211
        ]
      },
      "properties": {
        "marker-symbol": "doctor-15",
        "marker-color": "#000000",
        "name": "Yamanaka Vet Clinic",
        "address": "629-2 Kurokamichō, Sasebo-shi, Nagasaki-ken 857-1152",
        "telephone": "0956-34-0331",
        "website": "",
        "english": "",
        "note": ""
      }
    }
  ]
}
